convert_markmonitor_domain_list_to_mozilla/__about__.py
convert_markmonitor_domain_list_to_mozilla/__init__.py
convert_markmonitor_domain_list_to_mozilla/myDomains.xls
convert_markmonitor_domain_list_to_mozilla-1.0.0.dist-info/METADATA
convert_markmonitor_domain_list_to_mozilla-1.0.0.dist-info/WHEEL
convert_markmonitor_domain_list_to_mozilla-1.0.0.dist-info/entry_points.txt
convert_markmonitor_domain_list_to_mozilla-1.0.0.dist-info/RECORD
